ziglang/__init__.py
ziglang-0.0.0.dist-info/METADATA
ziglang-0.0.0.dist-info/WHEEL
ziglang-0.0.0.dist-info/RECORD
