Metadata-Version: 2.1
Name: ziglang
Version: 0.0.0
Summary: Zig Programming Language
License: MIT
Classifier: License :: OSI Approved :: MIT License
Project-URL: Homepage, https://ziglang.org
Requires-Python: ~=3.5
